bottle_sslify.py
setup.py
Bottle_SSLify.egg-info/PKG-INFO
Bottle_SSLify.egg-info/SOURCES.txt
Bottle_SSLify.egg-info/dependency_links.txt
Bottle_SSLify.egg-info/requires.txt
Bottle_SSLify.egg-info/top_level.txt
test/test_basic.py