Metadata-Version: 1.0
Name: Bottle-SSLify
Version: 0.0.1
Summary: Force SSL on any Bottle app.
Home-page: https://github.com/ali01/bottle-sslify
Author: Ali Yahya
Author-email: alive@athena.ai
License: MIT License
Platform: any
Classifier: Environment :: Web Environment
Classifier: Intended Audience :: Developers
Classifier: License :: OSI Approved :: MIT License
Classifier: Operating System :: OS Independent
Classifier: Programming Language :: Python
Classifier: Topic :: Internet :: WWW/HTTP :: Dynamic Content
Classifier: Topic :: Software Development :: Libraries :: Python Modules
